epiccli/__init__.py
epiccli/cli.py
epiccli/core.py
epiccli/exceptions.py
epiccli/path.py
epiccli-2023.11.2.dist-info/LICENSE
epiccli-2023.11.2.dist-info/METADATA
epiccli-2023.11.2.dist-info/WHEEL
epiccli-2023.11.2.dist-info/entry_points.txt
epiccli-2023.11.2.dist-info/top_level.txt
epiccli-2023.11.2.dist-info/RECORD
