Metadata-Version: 2.1
Name: epiccli
Version: 2023.11.2
Summary: "A command line interface for EPIC HPC"
Home-page: https://github.com/zenotech/epic-cli
Author: "Zenotech Ltd"
Author-email: "support@zenotech.com"
License: BSD 3-Clause License
Classifier: License :: OSI Approved :: BSD License
Classifier: Programming Language :: Python :: 3
Classifier: Programming Language :: Python :: 3.6
Classifier: Programming Language :: Python :: 3.7
Classifier: Programming Language :: Python :: 3.8
License-File: LICENSE
Requires-Dist: pyepic >=1.0.6
Requires-Dist: Click
Requires-Dist: pyfiglet
